tests/__init__.py
ziim/__init__.py
ziim/example.py
ziim/module.py
Ziim.0.0.2-0.0.2.dist-info/LICENSE.txt
Ziim.0.0.2-0.0.2.dist-info/METADATA
Ziim.0.0.2-0.0.2.dist-info/WHEEL
Ziim.0.0.2-0.0.2.dist-info/top_level.txt
Ziim.0.0.2-0.0.2.dist-info/RECORD
