Metadata-Version: 2.1
Name: Ziim.0.0.2
Version: 0.0.2
Summary: Let your CLI find available solutions for errors / exceptions online on commands you hit, for you, no need open a Browser. and find something yourself
Home-page: https://github.com/sanix-darker/ziim
Author: Sanix-darker
Author-email: s4nixd@gmail.com
License: UNKNOWN
Platform: UNKNOWN
Classifier: Programming Language :: Python :: 3
Classifier: License :: OSI Approved :: MIT License
Classifier: Operating System :: OS Independent
Requires-Python: >=3.6
